lab-1/freq_divider.vhdl
library ieee;
use ieee.std_logic_1164.all;
use ieee.numeric_std.all;

entity freq_divider is

    port(
        config : in std_logic_vector(31 downto 0); 
        inclk  : in std_logic; 
        outclk : out std_logic;
        nReset  : in std_logic -- active low signal
    );

end entity freq_divider;

architecture behav of freq_divider is

    signal val : integer;

begin

    proc: process
    begin
        wait until inclk='1';
        if nReset='0' then
        
            val <= 0;
            outclk <= '0';
        
        else
            -- someday ill need to figure out how all these BS conversions work...
            if to_integer(unsigned(config)) = val then
                outclk <= '1';
                val <= 0;
            else
                outclk <= '0';
                val <= val + 1;
            end if;

        end if;
    end process;

end architecture behav;

lab-1/timing_generator.vhdl
library ieee;
use ieee.std_logic_1164.all;
use ieee.numeric_std.all;

entity timing_generator is

    port(
        config : in std_logic_vector(31 downto 0); -- how many clk cycles is 1 second
        Start  : in std_logic;    -- active high
        clk    : in std_logic;
        reset  : in std_logic;    -- light_control and timing_generator are reset indepenently
        LC_Start : out std_logic; -- signal light control to start
        LC_Tick  : out std_logic;  -- divides base frequency down to 1 Hz for light control
        LC_DoneFeedBack : in std_logic
    );

end entity timing_generator;

architecture behav of timing_generator is

    signal state : integer := 0;
    signal freqreset: std_logic;

begin

    -- config, inclk, outclk, nReset
    freqdiv: entity work.freq_divider(behav) 
        port map(config, clk, LC_Tick, freqreset);

    proc: process
    begin
        wait until clk='1';
        
        if reset='1' then
            state <= 0;
        else

            case state is

                when 0 => -- reset state

                    if Start='1' then
                        LC_Start <='1';
                        freqreset <= '1';
                        state <= 1;
                    else
                        LC_Start <='0';
                        freqreset <= '0';
                    end if;

                when 1 => -- wait for slave to finish

                    LC_Start <= '0';-- should never last more than 1 (regular) clock cycle

                    if LC_DoneFeedBack='1' then
                        state <= 0;
                        freqreset <= '0';
                    end if;

                when others =>
                    state <= 11; -- unused by rest of FSM

            end case;

        end if;
    end process;

end architecture behav;

lab-1/light_control.vhdl
library ieee;
use ieee.std_logic_1164.all;
use ieee.numeric_std.all;


entity light_control is

    port(
        Reset : in std_logic; -- active high
        Tick  : in std_logic; -- expects a 1Hz signal
        Start : in std_logic;
        cRed, cYel, cGrn : out std_logic;
        done_signal : out std_logic -- tell controlling circuitry that we are done
    );

end entity light_control;

architecture behav of light_control is

    signal state : integer;

begin

    proc: process
    begin
        wait until Tick='1';
        if Reset='1' then
            state <= 0;

            cRed <= '1';
            cYel <= '0';
            cGrn <= '0';
            done_signal <= '0';

        else
            case state is
                when 0 =>

                    cRed <= '1';
                    cYel <= '0';
                    cGrn <= '0';
                    done_signal <= '0';

                    -- default behavior is to stay in state 0
                    if Start='1' then
                        state <= 2;
                    end if;

                when 1 =>
                    state <= 2;
                    cRed <= '1';
                    cYel <= '0';
                    cGrn <= '0';

                when 2 =>
                    state <= 3;
                    cRed <= '0';
                    cYel <= '1';
                    cGrn <= '0';

                when 3 =>
                    state <= 4;
                    cRed <= '0';
                    cYel <= '1';
                    cGrn <= '0';

                when 4 =>
                    state <= 5;
                    cRed <= '0';
                    cYel <= '0';
                    cGrn <= '1';

                when 5 =>
                    state <= 6;
                    cRed <= '0';
                    cYel <= '0';
                    cGrn <= '1';

                when 6 =>
                    state <= 0;
                    cRed <= '0';
                    cYel <= '0';
                    cGrn <= '1';
                    done_signal <= '1';
                
                when others => state <= 7; -- not used by the state machine which means it will wait for a reset
            end case;
        end if;
    end process;

end architecture behav;

lab-1/testbenchlab1.vhdl
library ieee;
use ieee.std_logic_1164.all;
use ieee.numeric_std.all;



entity testbenchlab1 is
    constant cyclespersecond : integer := 10;
end entity testbenchlab1;

architecture test_lab_1 of testbenchlab1 is

    signal sim_cRed, sim_cYel, sim_cGrn : std_logic;
    signal lc_done  : std_logic; -- light control -> timing gen
    signal lc_start : std_logic; -- timing gen -> light control
    signal lc_tick  : std_logic; -- timing gen -> light control
    signal reset    : std_logic; -- global reset
    signal start    : std_logic; -- -> timing gen
    signal clk      : std_logic; -- -> timing gen

    signal lc_tick_tmp : std_logic;

begin

    lc: entity work.light_control(behav) port map(
        reset, lc_tick, lc_start, sim_cRed, sim_cYel, sim_cGrn, lc_done);

    -- config, Start, clk, reset, LC_Start, LC_Tick, LC_DoneFeedback
    tg: entity work.timing_generator(behav) port map(
        std_logic_vector(to_unsigned(  cyclespersecond-1  , 32)),
        start, clk, reset,
        lc_start, lc_tick_tmp, lc_done);

    lc_tick <= reset or lc_tick_tmp;

    sim: process
    begin

        start <= '0';
        clk <= '0';

        -- reset everything (2 full cycles)
        reset <= '1';
        clk <= '1'; wait for 5 ns;
        clk <= '0'; wait for 5 ns;
        clk <= '1'; wait for 5 ns;
        clk <= '0'; wait for 5 ns;
        reset <= '0';

        for idk in 1 to 10 loop
            clk <= '1'; wait for 5 ns;
            clk <= '0'; wait for 5 ns;
        end loop;

        -- send the start signal for full tick cycles
        start <= '1';
        for idk in 1 to cyclespersecond loop
            clk <= '1'; wait for 5 ns;
            clk <= '0'; wait for 5 ns;    
        end loop;        
        start <= '0';

        -- wait for light control to finish
        for idx in 1 to 60 loop
            clk <= '1'; wait for 5 ns;
            clk <= '0'; wait for 5 ns;
        end loop;

        -- send the start signal
        start <= '1';
        for idk in 1 to cyclespersecond loop
            clk <= '1'; wait for 5 ns;
            clk <= '0'; wait for 5 ns;    
        end loop;        
        start <= '0';

        for idx in 1 to 60 loop
            clk <= '1'; wait for 5 ns;
            clk <= '0'; wait for 5 ns;
        end loop;

        wait;
    end process;

end architecture test_lab_1;

lab-1/waveform.vcd
$date
  Sun May  3 20:09:16 2020
$end
$version
  GHDL v0
$end
$timescale
  1 fs
$end
$scope module standard $end
$upscope $end
$scope module std_logic_1164 $end
$upscope $end
$scope module numeric_std $end
$upscope $end
$scope module testbenchlab1 $end
$var reg 1 ! sim_cred $end
$var reg 1 " sim_cyel $end
$var reg 1 # sim_cgrn $end
$var reg 1 $ lc_done $end
$var reg 1 % lc_start $end
$var reg 1 & lc_tick $end
$var reg 1 ' reset $end
$var reg 1 ( start $end
$var reg 1 ) clk $end
$var reg 1 * lc_tick_tmp $end
$scope module lc $end
$var reg 1 + reset $end
$var reg 1 , tick $end
$var reg 1 - start $end
$var reg 1 . cred $end
$var reg 1 / cyel $end
$var reg 1 0 cgrn $end
$var reg 1 1 done_signal $end
$var integer 32 2 state $end
$upscope $end
$scope module tg $end
$var reg 32 3 config[31:0] $end
$var reg 1 4 start $end
$var reg 1 5 clk $end
$var reg 1 6 reset $end
$var reg 1 7 lc_start $end
$var reg 1 8 lc_tick $end
$var reg 1 9 lc_donefeedback $end
$var integer 32 : state $end
$var reg 1 ; freqreset $end
$scope module freqdiv $end
$var reg 32 < config[31:0] $end
$var reg 1 = inclk $end
$var reg 1 > outclk $end
$var reg 1 ? nreset $end
$var integer 32 @ val $end
$upscope $end
$upscope $end
$upscope $end
$enddefinitions $end
#0
1!
0"
0#
0$
0%
1&
1'
0(
1)
0*
1+
1,
0-
1.
0/
00
01
b0 2
b00000000000000000000000000001001 3
04
15
16
07
08
09
b0 :
0;
b00000000000000000000000000001001 <
1=
0>
0?
b10000000000000000000000000000001 @
#5000000
0)
05
0=
#10000000
1)
15
1=
b0 @
#15000000
0)
05
0=
#20000000
0&
0'
1)
0+
0,
15
06
1;
1=
1?
#25000000
0)
05
0=
#30000000
1)
15
1=
b1 @
#35000000
0)
05
0=
#40000000
1)
15
1=
b10 @
#45000000
0)
05
0=
#50000000
1)
15
1=
b11 @
#55000000
0)
05
0=
#60000000
1)
15
1=
b100 @
#65000000
0)
05
0=
#70000000
1)
15
1=
b101 @
#75000000
0)
05
0=
#80000000
1)
15
1=
b110 @
#85000000
0)
05
0=
#90000000
1)
15
1=
b111 @
#95000000
0)
05
0=
#100000000
1)
15
1=
b1000 @
#105000000
0)
05
0=
#110000000
1)
15
1=
b1001 @
#115000000
0)
05
0=
#120000000
1%
1&
1(
1)
1*
1,
1-
b10 2
14
15
17
18
b1 :
1=
1>
b0 @
#125000000
0)
05
0=
#130000000
0&
1)
0*
0,
15
08
1=
0>
b1 @
#135000000
0)
05
0=
#140000000
1)
15
1=
b10 @
#145000000
0)
05
0=
#150000000
1)
15
1=
b11 @
#155000000
0)
05
0=
#160000000
1)
15
1=
b100 @
#165000000
0)
05
0=
#170000000
1)
15
1=
b101 @
#175000000
0)
05
0=
#180000000
1)
15
1=
b110 @
#185000000
0)
05
0=
#190000000
1)
15
1=
b111 @
#195000000
0)
05
0=
#200000000
1)
15
1=
b1000 @
#205000000
0)
05
0=
#210000000
1)
15
1=
b1001 @
#215000000
0)
05
0=
#220000000
0!
1"
0%
1&
0(
1)
1*
1,
0-
0.
1/
b11 2
04
15
07
18
1=
1>
b0 @
#225000000
0)
05
0=
#230000000
0&
1)
0*
0,
15
08
1=
0>
b1 @
#235000000
0)
05
0=
#240000000
1)
15
1=
b10 @
#245000000
0)
05
0=
#250000000
1)
15
1=
b11 @
#255000000
0)
05
0=
#260000000
1)
15
1=
b100 @
#265000000
0)
05
0=
#270000000
1)
15
1=
b101 @
#275000000
0)
05
0=
#280000000
1)
15
1=
b110 @
#285000000
0)
05
0=
#290000000
1)
15
1=
b111 @
#295000000
0)
05
0=
#300000000
1)
15
1=
b1000 @
#305000000
0)
05
0=
#310000000
1)
15
1=
b1001 @
#315000000
0)
05
0=
#320000000
1&
1)
1*
1,
b100 2
15
18
1=
1>
b0 @
#325000000
0)
05
0=
#330000000
0&
1)
0*
0,
15
08
1=
0>
b1 @
#335000000
0)
05
0=
#340000000
1)
15
1=
b10 @
#345000000
0)
05
0=
#350000000
1)
15
1=
b11 @
#355000000
0)
05
0=
#360000000
1)
15
1=
b100 @
#365000000
0)
05
0=
#370000000
1)
15
1=
b101 @
#375000000
0)
05
0=
#380000000
1)
15
1=
b110 @
#385000000
0)
05
0=
#390000000
1)
15
1=
b111 @
#395000000
0)
05
0=
#400000000
1)
15
1=
b1000 @
#405000000
0)
05
0=
#410000000
1)
15
1=
b1001 @
#415000000
0)
05
0=
#420000000
0"
1#
1&
1)
1*
1,
0/
10
b101 2
15
18
1=
1>
b0 @
#425000000
0)
05
0=
#430000000
0&
1)
0*
0,
15
08
1=
0>
b1 @
#435000000
0)
05
0=
#440000000
1)
15
1=
b10 @
#445000000
0)
05
0=
#450000000
1)
15
1=
b11 @
#455000000
0)
05
0=
#460000000
1)
15
1=
b100 @
#465000000
0)
05
0=
#470000000
1)
15
1=
b101 @
#475000000
0)
05
0=
#480000000
1)
15
1=
b110 @
#485000000
0)
05
0=
#490000000
1)
15
1=
b111 @
#495000000
0)
05
0=
#500000000
1)
15
1=
b1000 @
#505000000
0)
05
0=
#510000000
1)
15
1=
b1001 @
#515000000
0)
05
0=
#520000000
1&
1)
1*
1,
b110 2
15
18
1=
1>
b0 @
#525000000
0)
05
0=
#530000000
0&
1)
0*
0,
15
08
1=
0>
b1 @
#535000000
0)
05
0=
#540000000
1)
15
1=
b10 @
#545000000
0)
05
0=
#550000000
1)
15
1=
b11 @
#555000000
0)
05
0=
#560000000
1)
15
1=
b100 @
#565000000
0)
05
0=
#570000000
1)
15
1=
b101 @
#575000000
0)
05
0=
#580000000
1)
15
1=
b110 @
#585000000
0)
05
0=
#590000000
1)
15
1=
b111 @
#595000000
0)
05
0=
#600000000
1)
15
1=
b1000 @
#605000000
0)
05
0=
#610000000
1)
15
1=
b1001 @
#615000000
0)
05
0=
#620000000
1$
1&
1)
1*
1,
11
b0 2
15
18
19
1=
1>
b0 @
#625000000
0)
05
0=
#630000000
0&
1)
0*
0,
15
08
b0 :
1=
0>
b1 @
#635000000
0)
05
0=
#640000000
1)
15
1=
b10 @
#645000000
0)
05
0=
#650000000
1)
15
1=
b11 @
#655000000
0)
05
0=
#660000000
1)
15
1=
b100 @
#665000000
0)
05
0=
#670000000
1)
15
1=
b101 @
#675000000
0)
05
0=
#680000000
1)
15
1=
b110 @
#685000000
0)
05
0=
#690000000
1)
15
1=
b111 @
#695000000
0)
05
0=
#700000000
1)
15
1=
b1000 @
#705000000
0)
05
0=
#710000000
1)
15
1=
b1001 @
#715000000
0)
05
0=
#720000000
1!
0#
0$
1&
1)
1*
1,
1.
00
01
15
18
09
1=
1>
b0 @
#725000000
0)
05
0=
#730000000
0&
1)
0*
0,
15
08
1=
0>
b1 @
#735000000
0)
05
0=
#740000000
1)
15
1=
b10 @
#745000000
0)
05
0=
#750000000
1)
15
1=
b11 @
#755000000
0)
05
0=
#760000000
1)
15
1=
b100 @
#765000000
0)
05
0=
#770000000
1)
15
1=
b101 @
#775000000
0)
05
0=
#780000000
1)
15
1=
b110 @
#785000000
0)
05
0=
#790000000
1)
15
1=
b111 @
#795000000
0)
05
0=
#800000000
1)
15
1=
b1000 @
#805000000
0)
05
0=
#810000000
1)
15
1=
b1001 @
#815000000
0)
05
0=
#820000000
1%
1&
1(
1)
1*
1,
1-
b10 2
14
15
17
18
b1 :
1=
1>
b0 @
#825000000
0)
05
0=
#830000000
0&
1)
0*
0,
15
08
1=
0>
b1 @
#835000000
0)
05
0=
#840000000
1)
15
1=
b10 @
#845000000
0)
05
0=
#850000000
1)
15
1=
b11 @
#855000000
0)
05
0=
#860000000
1)
15
1=
b100 @
#865000000
0)
05
0=
#870000000
1)
15
1=
b101 @
#875000000
0)
05
0=
#880000000
1)
15
1=
b110 @
#885000000
0)
05
0=
#890000000
1)
15
1=
b111 @
#895000000
0)
05
0=
#900000000
1)
15
1=
b1000 @
#905000000
0)
05
0=
#910000000
1)
15
1=
b1001 @
#915000000
0)
05
0=
#920000000
0!
1"
0%
1&
0(
1)
1*
1,
0-
0.
1/
b11 2
04
15
07
18
1=
1>
b0 @
#925000000
0)
05
0=
#930000000
0&
1)
0*
0,
15
08
1=
0>
b1 @
#935000000
0)
05
0=
#940000000
1)
15
1=
b10 @
#945000000
0)
05
0=
#950000000
1)
15
1=
b11 @
#955000000
0)
05
0=
#960000000
1)
15
1=
b100 @
#965000000
0)
05
0=
#970000000
1)
15
1=
b101 @
#975000000
0)
05
0=
#980000000
1)
15
1=
b110 @
#985000000
0)
05
0=
#990000000
1)
15
1=
b111 @
#995000000
0)
05
0=
#1000000000
1)
15
1=
b1000 @
#1005000000
0)
05
0=
#1010000000
1)
15
1=
b1001 @
#1015000000
0)
05
0=
#1020000000
1&
1)
1*
1,
b100 2
15
18
1=
1>
b0 @
#1025000000
0)
05
0=
#1030000000
0&
1)
0*
0,
15
08
1=
0>
b1 @
#1035000000
0)
05
0=
#1040000000
1)
15
1=
b10 @
#1045000000
0)
05
0=
#1050000000
1)
15
1=
b11 @
#1055000000
0)
05
0=
#1060000000
1)
15
1=
b100 @
#1065000000
0)
05
0=
#1070000000
1)
15
1=
b101 @
#1075000000
0)
05
0=
#1080000000
1)
15
1=
b110 @
#1085000000
0)
05
0=
#1090000000
1)
15
1=
b111 @
#1095000000
0)
05
0=
#1100000000
1)
15
1=
b1000 @
#1105000000
0)
05
0=
#1110000000
1)
15
1=
b1001 @
#1115000000
0)
05
0=
#1120000000
0"
1#
1&
1)
1*
1,
0/
10
b101 2
15
18
1=
1>
b0 @
#1125000000
0)
05
0=
#1130000000
0&
1)
0*
0,
15
08
1=
0>
b1 @
#1135000000
0)
05
0=
#1140000000
1)
15
1=
b10 @
#1145000000
0)
05
0=
#1150000000
1)
15
1=
b11 @
#1155000000
0)
05
0=
#1160000000
1)
15
1=
b100 @
#1165000000
0)
05
0=
#1170000000
1)
15
1=
b101 @
#1175000000
0)
05
0=
#1180000000
1)
15
1=
b110 @
#1185000000
0)
05
0=
#1190000000
1)
15
1=
b111 @
#1195000000
0)
05
0=
#1200000000
1)
15
1=
b1000 @
#1205000000
0)
05
0=
#1210000000
1)
15
1=
b1001 @
#1215000000
0)
05
0=
#1220000000
1&
1)
1*
1,
b110 2
15
18
1=
1>
b0 @
#1225000000
0)
05
0=
#1230000000
0&
1)
0*
0,
15
08
1=
0>
b1 @
#1235000000
0)
05
0=
#1240000000
1)
15
1=
b10 @
#1245000000
0)
05
0=
#1250000000
1)
15
1=
b11 @
#1255000000
0)
05
0=
#1260000000
1)
15
1=
b100 @
#1265000000
0)
05
0=
#1270000000
1)
15
1=
b101 @
#1275000000
0)
05
0=
#1280000000
1)
15
1=
b110 @
#1285000000
0)
05
0=
#1290000000
1)
15
1=
b111 @
#1295000000
0)
05
0=
#1300000000
1)
15
1=
b1000 @
#1305000000
0)
05
0=
#1310000000
1)
15
1=
b1001 @
#1315000000
0)
05
0=
#1320000000
1$
1&
1)
1*
1,
11
b0 2
15
18
19
1=
1>
b0 @
#1325000000
0)
05
0=
#1330000000
0&
1)
0*
0,
15
08
b0 :
1=
0>
b1 @
#1335000000
0)
05
0=
#1340000000
1)
15
1=
b10 @
#1345000000
0)
05
0=
#1350000000
1)
15
1=
b11 @
#1355000000
0)
05
0=
#1360000000
1)
15
1=
b100 @
#1365000000
0)
05
0=
#1370000000
1)
15
1=
b101 @
#1375000000
0)
05
0=
#1380000000
1)
15
1=
b110 @
#1385000000
0)
05
0=
#1390000000
1)
15
1=
b111 @
#1395000000
0)
05
0=
#1400000000
1)
15
1=
b1000 @
#1405000000
0)
05
0=
#1410000000
1)
15
1=
b1001 @
#1415000000
0)
05
0=
#1420000000
1!
0#
0$
1&
1)
1*
1,
1.
00
01
15
18
09
1=
1>
b0 @
#1425000000
0)
05
0=
#1430000000
0&
1)
0*
0,
15
08
1=
0>
b1 @
#1435000000
0)
05
0=
#1440000000
1)
15
1=
b10 @
#1445000000
0)
05
0=
#1450000000
1)
15
1=
b11 @
#1455000000
0)
05
0=
#1460000000
1)
15
1=
b100 @
#1465000000
0)
05
0=
#1470000000
1)
15
1=
b101 @
#1475000000
0)
05
0=
#1480000000
1)
15
1=
b110 @
#1485000000
0)
05
0=
#1490000000
1)
15
1=
b111 @
#1495000000
0)
05
0=
#1500000000
1)
15
1=
b1000 @
#1505000000
0)
05
0=
#1510000000
1)
15
1=
b1001 @
