lab-1/freq_divider.vhdl
library ieee;
use ieee.std_logic_1164.all;
use ieee.numeric_std.all;

entity freq_divider is

    port(
        config : in std_logic_vector(31 downto 0); 
        inclk  : in std_logic; 
        outclk : out std_logic;
        nReset  : in std_logic -- active low signal
    );

end entity freq_divider;

architecture behav of freq_divider is

    signal val : integer;

begin

    proc: process
    begin
        wait until inclk='1';
        if nReset='0' then
        
            val <= 0;
            outclk <= '0';
        
        else
            -- someday ill need to figure out how all these BS conversions work...
            if to_integer(unsigned(config)) = val then
                outclk <= '1';
                val <= 0;
            else
                outclk <= '0';
                val <= val + 1;
            end if;

        end if;
    end process;

end architecture behav;

lab-1/timing_generator.vhdl
library ieee;
use ieee.std_logic_1164.all;
use ieee.numeric_std.all;

entity timing_generator is

    port(
        config : in std_logic_vector(31 downto 0); -- how many clk cycles is 1 second
        Start  : in std_logic;    -- active high
        clk    : in std_logic;
        reset  : in std_logic;    -- light_control and timing_generator are reset indepenently
        LC_Start : out std_logic; -- signal light control to start
        LC_Tick  : out std_logic;  -- divides base frequency down to 1 Hz for light control
        LC_DoneFeedBack : in std_logic
    );

end entity timing_generator;

architecture behav of timing_generator is

    signal state : integer := 0;
    signal freqreset: std_logic;

begin

    -- config, inclk, outclk, nReset
    freqdiv: entity work.freq_divider(behav) 
        port map(config, clk, LC_Tick, freqreset);

    proc: process
    begin
        wait until clk='1';
        
        if reset='1' then
            state <= 0;
        else

            case state is

                when 0 => -- reset state

                    if Start='1' then
                        LC_Start <='1';
                        freqreset <= '1';
                        state <= 1;
                    else
                        LC_Start <='0';
                        freqreset <= '0';
                    end if;

                when 1 => -- wait for slave to finish

                    LC_Start <= '0';-- should never last more than 1 (regular) clock cycle

                    if LC_DoneFeedBack='1' then
                        state <= 0;
                        freqreset <= '0';
                    end if;

                when others =>
                    state <= 11; -- unused by rest of FSM

            end case;

        end if;
    end process;

end architecture behav;

lab-1/light_control.vhdl
library ieee;
use ieee.std_logic_1164.all;
use ieee.numeric_std.all;


entity light_control is

    port(
        Reset : in std_logic; -- active high
        Tick  : in std_logic; -- expects a 1Hz signal
        Start : in std_logic;
        cRed, cYel, cGrn : out std_logic;
        done_signal : out std_logic -- tell controlling circuitry that we are done
    );

end entity light_control;

architecture behav of light_control is

    signal state : integer;

begin

    proc: process
    begin
        wait until Tick='1';
        if Reset='1' then
            state <= 0;

            cRed <= '1';
            cYel <= '0';
            cGrn <= '0';
            done_signal <= '0';

        else
            case state is
                when 0 =>

                    cRed <= '1';
                    cYel <= '0';
                    cGrn <= '0';
                    done_signal <= '0';

                    -- default behavior is to stay in state 0
                    if Start='1' then
                        state <= 2;
                    end if;

                when 1 =>
                    state <= 2;
                    cRed <= '1';
                    cYel <= '0';
                    cGrn <= '0';

                when 2 =>
                    state <= 3;
                    cRed <= '0';
                    cYel <= '1';
                    cGrn <= '0';

                when 3 =>
                    state <= 4;
                    cRed <= '0';
                    cYel <= '1';
                    cGrn <= '0';

                when 4 =>
                    state <= 5;
                    cRed <= '0';
                    cYel <= '0';
                    cGrn <= '1';

                when 5 =>
                    state <= 6;
                    cRed <= '0';
                    cYel <= '0';
                    cGrn <= '1';

                when 6 =>
                    state <= 0;
                    cRed <= '0';
                    cYel <= '0';
                    cGrn <= '1';
                    done_signal <= '1';
                
                when others => state <= 7; -- not used by the state machine which means it will wait for a reset
            end case;
        end if;
    end process;

end architecture behav;

lab-1/testbenchlab1.vhdl
library ieee;
use ieee.std_logic_1164.all;
use ieee.numeric_std.all;

entity testbenchlab1 is
end entity testbenchlab1;

architecture test_lab_1 of testbenchlab1 is

    signal sim_cRed, sim_cYel, sim_cGrn : std_logic;
    signal lc_done  : std_logic; -- light control -> timing gen
    signal lc_start : std_logic; -- timing gen -> light control
    signal lc_tick  : std_logic; -- timing gen -> light control
    signal reset    : std_logic; -- global reset
    signal start    : std_logic; -- -> timing gen
    signal clk      : std_logic; -- -> timing gen

    signal lc_tick_tmp : std_logic;

begin

    lc: entity work.light_control(behav) port map(
        reset, lc_tick, lc_start, sim_cRed, sim_cYel, sim_cGrn, lc_done);

    -- config, Start, clk, reset, LC_Start, LC_Tick, LC_DoneFeedback
    tg: entity work.timing_generator(behav) port map(
        std_logic_vector(to_unsigned(  4  , 32)),
        start, clk, reset,
        lc_start, lc_tick_tmp, lc_done);

    lc_tick <= reset or lc_tick_tmp;

    sim: process
    begin

        reset <= '1';
        start <= '0';
        clk <= '0';

        -- reset everything
        clk <= '1'; wait for 5 ns;
        clk <= '0'; wait for 5 ns;

        reset <= '0'; wait for 5 ns;

        -- send the start signal
        start <= '1';
        clk <= '1'; wait for 5 ns;
        clk <= '0'; wait for 5 ns;
        start <= '0';

        for idx in 1 to 80 loop
            clk <= '1'; wait for 5 ns;
            clk <= '0'; wait for 5 ns;
        end loop;


        wait;

    end process;

end architecture test_lab_1;

lab-1/waveform.vcd
$date
  Sun Feb  9 23:08:01 2020
$end
$version
  GHDL v0
$end
$timescale
  1 fs
$end
$scope module standard $end
$upscope $end
$scope module std_logic_1164 $end
$upscope $end
$scope module numeric_std $end
$upscope $end
$scope module testbenchlab1 $end
$var reg 1 ! sim_cred $end
$var reg 1 " sim_cyel $end
$var reg 1 # sim_cgrn $end
$var reg 1 $ lc_done $end
$var reg 1 % lc_start $end
$var reg 1 & lc_tick $end
$var reg 1 ' reset $end
$var reg 1 ( start $end
$var reg 1 ) clk $end
$var reg 1 * lc_tick_tmp $end
$scope module lc $end
$var reg 1 + reset $end
$var reg 1 , tick $end
$var reg 1 - start $end
$var reg 1 . cred $end
$var reg 1 / cyel $end
$var reg 1 0 cgrn $end
$var reg 1 1 done_signal $end
$var integer 32 2 state $end
$upscope $end
$scope module tg $end
$var reg 32 3 config[31:0] $end
$var reg 1 4 start $end
$var reg 1 5 clk $end
$var reg 1 6 reset $end
$var reg 1 7 lc_start $end
$var reg 1 8 lc_tick $end
$var reg 1 9 lc_donefeedback $end
$var integer 32 : state $end
$var reg 1 ; freqreset $end
$scope module freqdiv $end
$var reg 32 < config[31:0] $end
$var reg 1 = inclk $end
$var reg 1 > outclk $end
$var reg 1 ? nreset $end
$var integer 32 @ val $end
$upscope $end
$upscope $end
$upscope $end
$enddefinitions $end
#0
1!
0"
0#
0$
U%
1&
1'
0(
1)
0*
1+
1,
U-
1.
0/
00
01
b0 2
b00000000000000000000000000000100 3
04
15
16
U7
08
09
b0 :
U;
b00000000000000000000000000000100 <
1=
0>
U?
b10000000000000000000000000000001 @
#5000000
0)
05
0=
#10000000
0&
0'
0+
0,
06
#15000000
1%
1(
1)
1-
14
15
17
b1 :
1;
1=
1?
b10000000000000000000000000000010 @
#20000000
0)
05
0=
#25000000
0%
0(
1)
0-
04
15
07
1=
b10000000000000000000000000000011 @
#30000000
0)
05
0=
#35000000
1)
15
1=
b10000000000000000000000000000100 @
#40000000
0)
05
0=
#45000000
1)
15
1=
b10000000000000000000000000000101 @
#50000000
0)
05
0=
#55000000
1)
15
1=
b10000000000000000000000000000110 @
#60000000
0)
05
0=
#65000000
1)
15
1=
b10000000000000000000000000000111 @
#70000000
0)
05
0=
#75000000
1)
15
1=
b10000000000000000000000000001000 @
#80000000
0)
05
0=
#85000000
1)
15
1=
b10000000000000000000000000001001 @
#90000000
0)
05
0=
#95000000
1)
15
1=
b10000000000000000000000000001010 @
#100000000
0)
05
0=
#105000000
1)
15
1=
b10000000000000000000000000001011 @
#110000000
0)
05
0=
#115000000
1)
15
1=
b10000000000000000000000000001100 @
#120000000
0)
05
0=
#125000000
1)
15
1=
b10000000000000000000000000001101 @
#130000000
0)
05
0=
#135000000
1)
15
1=
b10000000000000000000000000001110 @
#140000000
0)
05
0=
#145000000
1)
15
1=
b10000000000000000000000000001111 @
#150000000
0)
05
0=
#155000000
1)
15
1=
b10000000000000000000000000010000 @
#160000000
0)
05
0=
#165000000
1)
15
1=
b10000000000000000000000000010001 @
#170000000
0)
05
0=
#175000000
1)
15
1=
b10000000000000000000000000010010 @
#180000000
0)
05
0=
#185000000
1)
15
1=
b10000000000000000000000000010011 @
#190000000
0)
05
0=
#195000000
1)
15
1=
b10000000000000000000000000010100 @
#200000000
0)
05
0=
#205000000
1)
15
1=
b10000000000000000000000000010101 @
#210000000
0)
05
0=
#215000000
1)
15
1=
b10000000000000000000000000010110 @
#220000000
0)
05
0=
#225000000
1)
15
1=
b10000000000000000000000000010111 @
#230000000
0)
05
0=
#235000000
1)
15
1=
b10000000000000000000000000011000 @
#240000000
0)
05
0=
#245000000
1)
15
1=
b10000000000000000000000000011001 @
#250000000
0)
05
0=
#255000000
1)
15
1=
b10000000000000000000000000011010 @
#260000000
0)
05
0=
#265000000
1)
15
1=
b10000000000000000000000000011011 @
#270000000
0)
05
0=
#275000000
1)
15
1=
b10000000000000000000000000011100 @
#280000000
0)
05
0=
#285000000
1)
15
1=
b10000000000000000000000000011101 @
#290000000
0)
05
0=
#295000000
1)
15
1=
b10000000000000000000000000011110 @
#300000000
0)
05
0=
#305000000
1)
15
1=
b10000000000000000000000000011111 @
#310000000
0)
05
0=
#315000000
1)
15
1=
b10000000000000000000000000100000 @
#320000000
0)
05
0=
#325000000
1)
15
1=
b10000000000000000000000000100001 @
#330000000
0)
05
0=
#335000000
1)
15
1=
b10000000000000000000000000100010 @
#340000000
0)
05
0=
#345000000
1)
15
1=
b10000000000000000000000000100011 @
#350000000
0)
05
0=
#355000000
1)
15
1=
b10000000000000000000000000100100 @
#360000000
0)
05
0=
#365000000
1)
15
1=
b10000000000000000000000000100101 @
#370000000
0)
05
0=
#375000000
1)
15
1=
b10000000000000000000000000100110 @
#380000000
0)
05
0=
#385000000
1)
15
1=
b10000000000000000000000000100111 @
#390000000
0)
05
0=
#395000000
1)
15
1=
b10000000000000000000000000101000 @
#400000000
0)
05
0=
#405000000
1)
15
1=
b10000000000000000000000000101001 @
#410000000
0)
05
0=
#415000000
1)
15
1=
b10000000000000000000000000101010 @
#420000000
0)
05
0=
#425000000
1)
15
1=
b10000000000000000000000000101011 @
#430000000
0)
05
0=
#435000000
1)
15
1=
b10000000000000000000000000101100 @
#440000000
0)
05
0=
#445000000
1)
15
1=
b10000000000000000000000000101101 @
#450000000
0)
05
0=
#455000000
1)
15
1=
b10000000000000000000000000101110 @
#460000000
0)
05
0=
#465000000
1)
15
1=
b10000000000000000000000000101111 @
#470000000
0)
05
0=
#475000000
1)
15
1=
b10000000000000000000000000110000 @
#480000000
0)
05
0=
#485000000
1)
15
1=
b10000000000000000000000000110001 @
#490000000
0)
05
0=
#495000000
1)
15
1=
b10000000000000000000000000110010 @
#500000000
0)
05
0=
#505000000
1)
15
1=
b10000000000000000000000000110011 @
#510000000
0)
05
0=
#515000000
1)
15
1=
b10000000000000000000000000110100 @
#520000000
0)
05
0=
#525000000
1)
15
1=
b10000000000000000000000000110101 @
#530000000
0)
05
0=
#535000000
1)
15
1=
b10000000000000000000000000110110 @
#540000000
0)
05
0=
#545000000
1)
15
1=
b10000000000000000000000000110111 @
#550000000
0)
05
0=
#555000000
1)
15
1=
b10000000000000000000000000111000 @
#560000000
0)
05
0=
#565000000
1)
15
1=
b10000000000000000000000000111001 @
#570000000
0)
05
0=
#575000000
1)
15
1=
b10000000000000000000000000111010 @
#580000000
0)
05
0=
#585000000
1)
15
1=
b10000000000000000000000000111011 @
#590000000
0)
05
0=
#595000000
1)
15
1=
b10000000000000000000000000111100 @
#600000000
0)
05
0=
#605000000
1)
15
1=
b10000000000000000000000000111101 @
#610000000
0)
05
0=
#615000000
1)
15
1=
b10000000000000000000000000111110 @
#620000000
0)
05
0=
#625000000
1)
15
1=
b10000000000000000000000000111111 @
#630000000
0)
05
0=
#635000000
1)
15
1=
b10000000000000000000000001000000 @
#640000000
0)
05
0=
#645000000
1)
15
1=
b10000000000000000000000001000001 @
#650000000
0)
05
0=
#655000000
1)
15
1=
b10000000000000000000000001000010 @
#660000000
0)
05
0=
#665000000
1)
15
1=
b10000000000000000000000001000011 @
#670000000
0)
05
0=
#675000000
1)
15
1=
b10000000000000000000000001000100 @
#680000000
0)
05
0=
#685000000
1)
15
1=
b10000000000000000000000001000101 @
#690000000
0)
05
0=
#695000000
1)
15
1=
b10000000000000000000000001000110 @
#700000000
0)
05
0=
#705000000
1)
15
1=
b10000000000000000000000001000111 @
#710000000
0)
05
0=
#715000000
1)
15
1=
b10000000000000000000000001001000 @
#720000000
0)
05
0=
#725000000
1)
15
1=
b10000000000000000000000001001001 @
#730000000
0)
05
0=
#735000000
1)
15
1=
b10000000000000000000000001001010 @
#740000000
0)
05
0=
#745000000
1)
15
1=
b10000000000000000000000001001011 @
#750000000
0)
05
0=
#755000000
1)
15
1=
b10000000000000000000000001001100 @
#760000000
0)
05
0=
#765000000
1)
15
1=
b10000000000000000000000001001101 @
#770000000
0)
05
0=
#775000000
1)
15
1=
b10000000000000000000000001001110 @
#780000000
0)
05
0=
#785000000
1)
15
1=
b10000000000000000000000001001111 @
#790000000
0)
05
0=
#795000000
1)
15
1=
b10000000000000000000000001010000 @
