lab-3/full_adder_rc.vhdl
library ieee;
use ieee.std_logic_1164.all;
use ieee.numeric_std.all;

-- full 1-bit adder
entity full_adder_rc is
    port(
        A    : in std_logic;
        B    : in std_logic;
        Sum  : out std_logic;
        Cin  : in std_logic;
        Cout : out std_logic
    );
end entity full_adder_rc;

architecture behav of full_adder_rc is
begin
    Sum <= A xor B xor Cin;
    Cout <= (A and B) or ((A xor B) and Cin);
end architecture behav;

lab-4/adder.vhdl
library ieee;
use ieee.std_logic_1164.all;
use ieee.numeric_std.all;

entity adder is

    generic(buswidth: integer := 8);

    port(
        A    : in  std_logic_vector(buswidth-1 downto 0);
        B    : in  std_logic_vector(buswidth-1 downto 0);
        Sum  : out std_logic_vector(buswidth-1 downto 0);
        Cin  : in  std_logic;
        Cout : out std_logic
    );

end entity adder;

architecture behav of adder is
    -- temporary holding place for carries
    signal c : std_logic_vector(buswidth downto 0);
begin

    fa_all:
        for i in 0 to buswidth-1 generate
            fa:
                entity work.full_adder_rc(behav)
                port map(A(i), B(i), Sum(i), c(i), c(i+1));
        end generate;

    c(0) <= Cin;
    Cout <= c(buswidth);

end architecture behav;

lab-4/d_ff.vhdl
library ieee;
use ieee.std_logic_1164.all;


entity d_ff is
    port(d, clk : in std_logic; q, nq : out std_logic);
end d_ff;

architecture basic_arch of d_ff is
begin
    
    ff_behavior: process(clk)
    begin

        if rising_edge(clk) then
            q <= d;
            nq <= not d;
        end if;

        --wait until clk='1';
        --q <= d;
        --nq <= not d;
    end process ff_behavior;

end architecture basic_arch;

lab-2/shift_register.vhdl
library ieee;
use ieee.std_logic_1164.all;
use ieee.numeric_std.all;

entity shift_register is

    generic(buswidth: integer := 8);

    port(
        D   : in  std_logic_vector(buswidth-1 downto 0);
        Q   : out std_logic_vector(buswidth-1 downto 0);
        clk : in std_logic;
        rd_nsft : in std_logic; -- 1:read, 0:shft
        enable  : in std_logic;
        Dsftin  : in std_logic;
        Dsftout : out std_logic
    );

end entity shift_register;

architecture behav of shift_register is
    signal din  : std_logic_vector(buswidth-1 downto 0);
    signal qout : std_logic_vector(buswidth-1 downto 0);
    signal clockand : std_logic;

begin

    clockand <= clk and enable;
    din(0) <= (Dsftin and not rd_nsft) or (D(0) and rd_nsft);

    Q <= qout;

    sr:
        for i in 0 to buswidth-1 generate
            sr_i:
                entity work.d_ff(basic_arch)
                port map(din(i), clockand, qout(i), open);
        end generate;

    clogic:
        for i in 1 to buswidth-1 generate
            din(i) <= (qout(i-1) and not rd_nsft) or (D(i) and rd_nsft);
        end generate;

    Dsftout <= qout(buswidth-1);

end architecture behav;

lab-4/q_register.vhdl
library ieee;
use ieee.std_logic_1164.all;
use ieee.numeric_std.all;

entity q_register is
    port(
        D    : in std_logic_vector(7 downto 0);
        Q    : out std_logic_vector(7 downto 0);
        clk  : in std_logic;
        Amsb : in std_logic;
        sh_rdnsft : in std_logic; -- 0:shift 1:read
        sh_en  : in std_logic;
        lsb_sel : in std_logic; -- 0:D0 1:Amsb
        sh_out  : out std_logic);
end entity q_register;

architecture behav of q_register is

    signal dff_out : std_logic;
    signal mux_out : std_logic;

begin

    Q(0) <= dff_out;

    mux_out <= (D(0) and not lsb_sel) or (Amsb and lsb_sel);

    dff: entity work.d_ff(basic_arch) port map(mux_out, clk, dff_out, open);

    shreg: entity work.shift_register(behav) generic map(7) 
    port map(
        D(7 downto 1),
        Q(7 downto 1),
        clk,
        sh_rdnsft,
        sh_en,
        dff_out,
        sh_out);

end architecture behav;

lab-3/selector.vhdl
library ieee;
use ieee.std_logic_1164.all;
use ieee.numeric_std.all;

entity selector is
    generic(buswidth: integer);

    port(
        A  : in std_logic_vector(buswidth-1 downto 0);
        Y  : out std_logic_vector(buswidth-1 downto 0);
        En : in std_logic
    );

end entity selector;

architecture behav of selector is

begin

    andgates:
        for i in 0 to buswidth-1 generate
            Y(i) <= A(i) and En;
        end generate;

end architecture behav;

lab-4/incrementer.vhdl
library ieee;
use ieee.std_logic_1164.all;
use ieee.numeric_std.all;

entity incrementer is
    generic(buswidth : integer);
    port(
        A    : in std_logic_vector(buswidth-1 downto 0);
        Ainc : out std_logic_vector(buswidth-1 downto 0));
end entity incrementer;

architecture behav of incrementer is

    signal Binput : std_logic_vector(buswidth-1 downto 0);

begin

    Binput(0) <= '1';
    gen1:
        for i in 1 to buswidth-1 generate
            Binput(i) <= '0';
        end generate;

    add:
        entity work.adder(behav)
        generic map(buswidth)
        port map(A, Binput, Ainc, '0', open);

end architecture behav;

lab-4/negate.vhdl
library ieee;
use ieee.std_logic_1164.all;
use ieee.numeric_std.all;

entity negate is

    generic(buswidth : integer);
    port(
        A    : in  std_logic_vector(buswidth-1 downto 0);
        negA : out std_logic_vector(buswidth-1 downto 0));
end entity negate;

architecture behav of negate is

    signal Ainv : std_logic_vector(buswidth-1 downto 0);

begin

    inverta:
        for i in 0 to buswidth-1 generate
            Ainv(i) <= not A(i);
        end generate;

    add: 
        entity work.incrementer(behav)
        generic map(buswidth)
        port map(Ainv, negA);

end architecture behav;

lab-3/reg.vhdl
library ieee;
use ieee.std_logic_1164.all;
use ieee.numeric_std.all;

entity reg is

    generic(buswidth: integer := 8);

    port(
        D     : in std_logic_vector(buswidth-1 downto 0);
        Q     : out std_logic_vector(buswidth-1 downto 0);
        nQ    : out std_logic_vector(buswidth-1 downto 0);
        clock : in std_logic
    );

end entity reg;

architecture behav of reg is
begin

    proc: process
    begin
        wait until clock='1';

        Q <= D;
        nQ <= not D;

    end process;

end architecture behav;

lab-4/zero_extender.vhdl
library ieee;
use ieee.std_logic_1164.all;
use ieee.numeric_std.all;

entity zero_extender is
    generic(inwidth : integer; outwidth : integer);
    port(
        A : in  std_logic_vector(inwidth-1 downto 0);
        Y : out std_logic_vector(outwidth-1 downto 0));
end entity zero_extender;

architecture behav of zero_extender is

begin

    Y(inwidth-1 downto 0) <= A;
    Y(outwidth-1 downto inwidth) <= (others => '0');

end architecture behav;

lab-4/datapath.vhdl
library ieee;
use ieee.std_logic_1164.all;
use ieee.numeric_std.all;

entity datapath is

    port(
        divisor   : in  std_logic_vector(3 downto 0);
        dividend  : in  std_logic_vector(7 downto 0);
        quotient  : out std_logic_vector(7 downto 0);
        remainder : out std_logic_vector(7 downto 0);
        
        m_clock   : in std_logic;
        a_clock   : in std_logic;
        q_clock   : in std_logic;
        fb_enable : in std_logic; -- feedback loop enable (goes to A input)
        
        A_rdnsft  : in std_logic;
        A_enable  : in std_logic;

        Q_shreg_rdnsft : in std_logic;
        Q_lsb_sel : in std_logic;
        Q_shreg_en : in std_logic;
        
        add_msb : out std_logic);

end entity;

architecture behav of datapath is

    signal divisor_se : std_logic_vector(7 downto 0);
    signal M_q : std_logic_vector(7 downto 0);
    signal M_out : std_logic_vector(7 downto 0);
    signal A_out : std_logic_vector(7 downto 0);

    signal feedback    : std_logic_vector(7 downto 0);
    signal feedback_en : std_logic_vector(7 downto 0);

    signal q_sftout   : std_logic;
    signal fbloop_msb : std_logic;

begin

    d_ze: entity work.zero_extender(behav) generic map(4, 8) port map(divisor, divisor_se);
    M:    entity work.reg(behav) generic map(8) port map(divisor_se, M_q, open, m_clock);
    Mneg: entity work.negate(behav) generic map(8) port map(divisor_se, M_out);

    fben: entity work.selector(behav) generic map(8) port map(feedback, feedback_en, fb_enable);

    A: 
        entity work.shift_register(behav) 
        generic map(8) 
        port map(
            feedback_en, A_out, a_clock, A_rdnsft, A_enable, q_sftout, open);

    remainder <= feedback;
    add_msb <= feedback(7);

    Q: 
        entity work.q_register(behav)
        port map(
            dividend,
            quotient,
            q_clock,
            feedback(7), -- Amsb
            Q_shreg_rdnsft,
            Q_shreg_en,
            Q_lsb_sel,
            q_sftout);

    fbloop_msb <= not feedback(7);

    add: entity work.adder(behav) generic map(8) port map(M_out, A_out, feedback, '0', open);

end architecture behav;

lab-4/testbench_datapath.vhdl
library ieee;
use ieee.std_logic_1164.all;
use ieee.numeric_std.all;

entity testbench_datapath is
end entity testbench_datapath;

architecture behav of testbench_datapath is

    signal divisor   : std_logic_vector(3 downto 0);
    signal dividend  : std_logic_vector(7 downto 0);
    signal quotient  : std_logic_vector(7 downto 0);
    signal remainder : std_logic_vector(7 downto 0);
    
    signal m_clock   : std_logic;
    signal a_clock   : std_logic;
    signal q_clock   : std_logic;
    signal fb_enable : std_logic; -- feedback loop enable (goes to A input) also helps clear A
    
    signal A_rdnsft : std_logic; -- 1:read 0:shift
    signal A_enable : std_logic;

    signal Q_shreg_rdnsft : std_logic;
    signal Q_lsb_sel  : std_logic;
    signal Q_shreg_en : std_logic;

    signal add_msb : std_logic;

begin

    ent:
        entity work.datapath(behav)
        port map(
            divisor, dividend, quotient, remainder,
            m_clock, a_clock, q_clock, fb_enable,
            A_rdnsft, A_enable,
            Q_shreg_rdnsft, Q_lsb_sel, Q_shreg_en);

    proc: process
    begin

        dividend <= "00001011"; --  11
        divisor  <= "0011";     -- / 3

        A_enable <= '1';
        A_rdnsft <= '1'; -- read
        fb_enable <= '0'; -- A needs zero-init
        Q_shreg_en <= '1';
        Q_shreg_rdnsft <= '1'; -- read Q        
        Q_lsb_sel <= '0'; -- read D(0)

        m_clock <= '0';
        a_clock <= '0';
        q_clock <= '0';
        wait for 5 ns;
        m_clock <= '1';
        a_clock <= '1';
        q_clock <= '1';
        wait for 5 ns;

        for i in 0 to 7 loop

            -- shift AQ
            A_rdnsft <= '0';       -- shift A
            Q_shreg_rdnsft <= '0'; -- shift Q      

            m_clock <= '0';
            a_clock <= '0';
            q_clock <= '0';
            wait for 5 ns;
            m_clock <= '1';
            a_clock <= '1';
            q_clock <= '1';
            wait for 5 ns;

            if add_msb = '1' then
                
            else
                
            end if;

        end loop;

        wait;
    end process;

end architecture behav;

lab-4/waveform.vcd
$date
  Wed May  6 21:21:08 2020
$end
$version
  GHDL v0
$end
$timescale
  1 fs
$end
$scope module standard $end
$upscope $end
$scope module std_logic_1164 $end
$upscope $end
$scope module numeric_std $end
$upscope $end
$scope module testbench_datapath $end
$var reg 4 ! divisor[3:0] $end
$var reg 8 " dividend[7:0] $end
$var reg 8 # quotient[7:0] $end
$var reg 8 $ remainder[7:0] $end
$var reg 1 % m_clock $end
$var reg 1 & a_clock $end
$var reg 1 ' q_clock $end
$var reg 1 ( fb_enable $end
$var reg 1 ) a_rdnsft $end
$var reg 1 * a_enable $end
$var reg 1 + q_shreg_rdnsft $end
$var reg 1 , q_lsb_sel $end
$var reg 1 - q_shreg_en $end
$var reg 1 . add_msb $end
$scope module ent $end
$var reg 4 / divisor[3:0] $end
$var reg 8 0 dividend[7:0] $end
$var reg 8 1 quotient[7:0] $end
$var reg 8 2 remainder[7:0] $end
$var reg 1 3 m_clock $end
$var reg 1 4 a_clock $end
$var reg 1 5 q_clock $end
$var reg 1 6 fb_enable $end
$var reg 1 7 a_rdnsft $end
$var reg 1 8 a_enable $end
$var reg 1 9 q_shreg_rdnsft $end
$var reg 1 : q_lsb_sel $end
$var reg 1 ; q_shreg_en $end
$var reg 1 < add_msb $end
$var reg 8 = divisor_se[7:0] $end
$var reg 8 > m_q[7:0] $end
$var reg 8 ? m_out[7:0] $end
$var reg 8 @ a_out[7:0] $end
$var reg 8 A feedback[7:0] $end
$var reg 8 B feedback_en[7:0] $end
$var reg 1 C q_sftout $end
$var reg 1 D fbloop_msb $end
$scope module d_ze $end
$var reg 4 E a[3:0] $end
$var reg 8 F y[7:0] $end
$upscope $end
$scope module m $end
$var reg 8 G d[7:0] $end
$var reg 8 H q[7:0] $end
$var reg 8 I nq[7:0] $end
$var reg 1 J clock $end
$upscope $end
$scope module mneg $end
$var reg 8 K a[7:0] $end
$var reg 8 L nega[7:0] $end
$var reg 8 M ainv[7:0] $end
$scope module inverta(0) $end
$upscope $end
$scope module inverta(1) $end
$upscope $end
$scope module inverta(2) $end
$upscope $end
$scope module inverta(3) $end
$upscope $end
$scope module inverta(4) $end
$upscope $end
$scope module inverta(5) $end
$upscope $end
$scope module inverta(6) $end
$upscope $end
$scope module inverta(7) $end
$upscope $end
$scope module add $end
$var reg 8 N a[7:0] $end
$var reg 8 O ainc[7:0] $end
$var reg 8 P binput[7:0] $end
$scope module gen1(1) $end
$upscope $end
$scope module gen1(2) $end
$upscope $end
$scope module gen1(3) $end
$upscope $end
$scope module gen1(4) $end
$upscope $end
$scope module gen1(5) $end
$upscope $end
$scope module gen1(6) $end
$upscope $end
$scope module gen1(7) $end
$upscope $end
$scope module add $end
$var reg 8 Q a[7:0] $end
$var reg 8 R b[7:0] $end
$var reg 8 S sum[7:0] $end
$var reg 1 T cin $end
$var reg 1 U cout $end
$var reg 9 V c[8:0] $end
$scope module fa_all(0) $end
$scope module fa $end
$var reg 1 W a $end
$var reg 1 X b $end
$var reg 1 Y sum $end
$var reg 1 Z cin $end
$var reg 1 [ cout $end
$upscope $end
$upscope $end
$scope module fa_all(1) $end
$scope module fa $end
$var reg 1 \ a $end
$var reg 1 ] b $end
$var reg 1 ^ sum $end
$var reg 1 _ cin $end
$var reg 1 ` cout $end
$upscope $end
$upscope $end
$scope module fa_all(2) $end
$scope module fa $end
$var reg 1 a a $end
$var reg 1 b b $end
$var reg 1 c sum $end
$var reg 1 d cin $end
$var reg 1 e cout $end
$upscope $end
$upscope $end
$scope module fa_all(3) $end
$scope module fa $end
$var reg 1 f a $end
$var reg 1 g b $end
$var reg 1 h sum $end
$var reg 1 i cin $end
$var reg 1 j cout $end
$upscope $end
$upscope $end
$scope module fa_all(4) $end
$scope module fa $end
$var reg 1 k a $end
$var reg 1 l b $end
$var reg 1 m sum $end
$var reg 1 n cin $end
$var reg 1 o cout $end
$upscope $end
$upscope $end
$scope module fa_all(5) $end
$scope module fa $end
$var reg 1 p a $end
$var reg 1 q b $end
$var reg 1 r sum $end
$var reg 1 s cin $end
$var reg 1 t cout $end
$upscope $end
$upscope $end
$scope module fa_all(6) $end
$scope module fa $end
$var reg 1 u a $end
$var reg 1 v b $end
$var reg 1 w sum $end
$var reg 1 x cin $end
$var reg 1 y cout $end
$upscope $end
$upscope $end
$scope module fa_all(7) $end
$scope module fa $end
$var reg 1 z a $end
$var reg 1 { b $end
$var reg 1 | sum $end
$var reg 1 } cin $end
$var reg 1 !" cout $end
$upscope $end
$upscope $end
$upscope $end
$upscope $end
$upscope $end
$scope module fben $end
$var reg 8 "" a[7:0] $end
$var reg 8 #" y[7:0] $end
$var reg 1 $" en $end
$scope module andgates(0) $end
$upscope $end
$scope module andgates(1) $end
$upscope $end
$scope module andgates(2) $end
$upscope $end
$scope module andgates(3) $end
$upscope $end
$scope module andgates(4) $end
$upscope $end
$scope module andgates(5) $end
$upscope $end
$scope module andgates(6) $end
$upscope $end
$scope module andgates(7) $end
$upscope $end
$upscope $end
$scope module a $end
$var reg 8 %" d[7:0] $end
$var reg 8 &" q[7:0] $end
$var reg 1 '" clk $end
$var reg 1 (" rd_nsft $end
$var reg 1 )" enable $end
$var reg 1 *" dsftin $end
$var reg 1 +" dsftout $end
$var reg 8 ," din[7:0] $end
$var reg 8 -" qout[7:0] $end
$var reg 1 ." clockand $end
$scope module sr(0) $end
$scope module sr_i $end
$var reg 1 /" d $end
$var reg 1 0" clk $end
$var reg 1 1" q $end
$var reg 1 2" nq $end
$upscope $end
$upscope $end
$scope module sr(1) $end
$scope module sr_i $end
$var reg 1 3" d $end
$var reg 1 4" clk $end
$var reg 1 5" q $end
$var reg 1 6" nq $end
$upscope $end
$upscope $end
$scope module sr(2) $end
$scope module sr_i $end
$var reg 1 7" d $end
$var reg 1 8" clk $end
$var reg 1 9" q $end
$var reg 1 :" nq $end
$upscope $end
$upscope $end
$scope module sr(3) $end
$scope module sr_i $end
$var reg 1 ;" d $end
$var reg 1 <" clk $end
$var reg 1 =" q $end
$var reg 1 >" nq $end
$upscope $end
$upscope $end
$scope module sr(4) $end
$scope module sr_i $end
$var reg 1 ?" d $end
$var reg 1 @" clk $end
$var reg 1 A" q $end
$var reg 1 B" nq $end
$upscope $end
$upscope $end
$scope module sr(5) $end
$scope module sr_i $end
$var reg 1 C" d $end
$var reg 1 D" clk $end
$var reg 1 E" q $end
$var reg 1 F" nq $end
$upscope $end
$upscope $end
$scope module sr(6) $end
$scope module sr_i $end
$var reg 1 G" d $end
$var reg 1 H" clk $end
$var reg 1 I" q $end
$var reg 1 J" nq $end
$upscope $end
$upscope $end
$scope module sr(7) $end
$scope module sr_i $end
$var reg 1 K" d $end
$var reg 1 L" clk $end
$var reg 1 M" q $end
$var reg 1 N" nq $end
$upscope $end
$upscope $end
$scope module clogic(1) $end
$upscope $end
$scope module clogic(2) $end
$upscope $end
$scope module clogic(3) $end
$upscope $end
$scope module clogic(4) $end
$upscope $end
$scope module clogic(5) $end
$upscope $end
$scope module clogic(6) $end
$upscope $end
$scope module clogic(7) $end
$upscope $end
$upscope $end
$scope module q $end
$var reg 8 O" d[7:0] $end
$var reg 8 P" q[7:0] $end
$var reg 1 Q" clk $end
$var reg 1 R" amsb $end
$var reg 1 S" sh_rdnsft $end
$var reg 1 T" sh_en $end
$var reg 1 U" lsb_sel $end
$var reg 1 V" sh_out $end
$var reg 1 W" dff_out $end
$var reg 1 X" mux_out $end
$scope module dff $end
$var reg 1 Y" d $end
$var reg 1 Z" clk $end
$var reg 1 [" q $end
$var reg 1 \" nq $end
$upscope $end
$scope module shreg $end
$var reg 7 ]" d[6:0] $end
$var reg 7 ^" q[6:0] $end
$var reg 1 _" clk $end
$var reg 1 `" rd_nsft $end
$var reg 1 a" enable $end
$var reg 1 b" dsftin $end
$var reg 1 c" dsftout $end
$var reg 7 d" din[6:0] $end
$var reg 7 e" qout[6:0] $end
$var reg 1 f" clockand $end
$scope module sr(0) $end
$scope module sr_i $end
$var reg 1 g" d $end
$var reg 1 h" clk $end
$var reg 1 i" q $end
$var reg 1 j" nq $end
$upscope $end
$upscope $end
$scope module sr(1) $end
$scope module sr_i $end
$var reg 1 k" d $end
$var reg 1 l" clk $end
$var reg 1 m" q $end
$var reg 1 n" nq $end
$upscope $end
$upscope $end
$scope module sr(2) $end
$scope module sr_i $end
$var reg 1 o" d $end
$var reg 1 p" clk $end
$var reg 1 q" q $end
$var reg 1 r" nq $end
$upscope $end
$upscope $end
$scope module sr(3) $end
$scope module sr_i $end
$var reg 1 s" d $end
$var reg 1 t" clk $end
$var reg 1 u" q $end
$var reg 1 v" nq $end
$upscope $end
$upscope $end
$scope module sr(4) $end
$scope module sr_i $end
$var reg 1 w" d $end
$var reg 1 x" clk $end
$var reg 1 y" q $end
$var reg 1 z" nq $end
$upscope $end
$upscope $end
$scope module sr(5) $end
$scope module sr_i $end
$var reg 1 {" d $end
$var reg 1 |" clk $end
$var reg 1 }" q $end
$var reg 1 !# nq $end
$upscope $end
$upscope $end
$scope module sr(6) $end
$scope module sr_i $end
$var reg 1 "# d $end
$var reg 1 ## clk $end
$var reg 1 $# q $end
$var reg 1 %# nq $end
$upscope $end
$upscope $end
$scope module clogic(1) $end
$upscope $end
$scope module clogic(2) $end
$upscope $end
$scope module clogic(3) $end
$upscope $end
$scope module clogic(4) $end
$upscope $end
$scope module clogic(5) $end
$upscope $end
$scope module clogic(6) $end
$upscope $end
$upscope $end
$upscope $end
$scope module add $end
$var reg 8 &# a[7:0] $end
$var reg 8 '# b[7:0] $end
$var reg 8 (# sum[7:0] $end
$var reg 1 )# cin $end
$var reg 1 *# cout $end
$var reg 9 +# c[8:0] $end
$scope module fa_all(0) $end
$scope module fa $end
$var reg 1 ,# a $end
$var reg 1 -# b $end
$var reg 1 .# sum $end
$var reg 1 /# cin $end
$var reg 1 0# cout $end
$upscope $end
$upscope $end
$scope module fa_all(1) $end
$scope module fa $end
$var reg 1 1# a $end
$var reg 1 2# b $end
$var reg 1 3# sum $end
$var reg 1 4# cin $end
$var reg 1 5# cout $end
$upscope $end
$upscope $end
$scope module fa_all(2) $end
$scope module fa $end
$var reg 1 6# a $end
$var reg 1 7# b $end
$var reg 1 8# sum $end
$var reg 1 9# cin $end
$var reg 1 :# cout $end
$upscope $end
$upscope $end
$scope module fa_all(3) $end
$scope module fa $end
$var reg 1 ;# a $end
$var reg 1 <# b $end
$var reg 1 =# sum $end
$var reg 1 ># cin $end
$var reg 1 ?# cout $end
$upscope $end
$upscope $end
$scope module fa_all(4) $end
$scope module fa $end
$var reg 1 @# a $end
$var reg 1 A# b $end
$var reg 1 B# sum $end
$var reg 1 C# cin $end
$var reg 1 D# cout $end
$upscope $end
$upscope $end
$scope module fa_all(5) $end
$scope module fa $end
$var reg 1 E# a $end
$var reg 1 F# b $end
$var reg 1 G# sum $end
$var reg 1 H# cin $end
$var reg 1 I# cout $end
$upscope $end
$upscope $end
$scope module fa_all(6) $end
$scope module fa $end
$var reg 1 J# a $end
$var reg 1 K# b $end
$var reg 1 L# sum $end
$var reg 1 M# cin $end
$var reg 1 N# cout $end
$upscope $end
$upscope $end
$scope module fa_all(7) $end
$scope module fa $end
$var reg 1 O# a $end
$var reg 1 P# b $end
$var reg 1 Q# sum $end
$var reg 1 R# cin $end
$var reg 1 S# cout $end
$upscope $end
$upscope $end
$upscope $end
$upscope $end
$upscope $end
$enddefinitions $end
#0
b0011 !
b00001011 "
bUUUUUUUU #
bUUUUUUUU $
0%
0&
0'
0(
1)
1*
1+
0,
1-
U.
b0011 /
b00001011 0
bUUUUUUUU 1
bUUUUUUUU 2
03
04
05
06
17
18
19
0:
1;
U<
b00000011 =
bUUUUUUUU >
b11111101 ?
bUUUUUUUU @
bUUUUUUUU A
b00000000 B
UC
UD
b0011 E
b00000011 F
b00000011 G
bUUUUUUUU H
bUUUUUUUU I
0J
b00000011 K
b11111101 L
b11111100 M
b11111100 N
b11111101 O
b00000001 P
b11111100 Q
b00000001 R
b11111101 S
0T
0U
b000000000 V
0W
1X
1Y
0Z
0[
0\
0]
0^
0_
0`
1a
0b
1c
0d
0e
1f
0g
1h
0i
0j
1k
0l
1m
0n
0o
1p
0q
1r
0s
0t
1u
0v
1w
0x
0y
1z
0{
1|
0}
0!"
bUUUUUUUU ""
b00000000 #"
0$"
b00000000 %"
bUUUUUUUU &"
0'"
1("
1)"
U*"
U+"
b00000000 ,"
bUUUUUUUU -"
0."
0/"
00"
U1"
U2"
03"
04"
U5"
U6"
07"
08"
U9"
U:"
0;"
0<"
U="
U>"
0?"
0@"
UA"
UB"
0C"
0D"
UE"
UF"
0G"
0H"
UI"
UJ"
0K"
0L"
UM"
UN"
b00001011 O"
bUUUUUUUU P"
0Q"
UR"
1S"
1T"
0U"
UV"
UW"
1X"
1Y"
0Z"
U["
U\"
b0000101 ]"
bUUUUUUU ^"
0_"
1`"
1a"
Ub"
Uc"
b0000101 d"
bUUUUUUU e"
0f"
1g"
0h"
Ui"
Uj"
0k"
0l"
Um"
Un"
1o"
0p"
Uq"
Ur"
0s"
0t"
Uu"
Uv"
0w"
0x"
Uy"
Uz"
0{"
0|"
U}"
U!#
0"#
0##
U$#
U%#
b11111101 &#
bUUUUUUUU '#
bUUUUUUUU (#
0)#
U*#
bUUUUUUUU0 +#
1,#
U-#
U.#
0/#
U0#
01#
U2#
U3#
U4#
U5#
16#
U7#
U8#
U9#
U:#
1;#
U<#
U=#
U>#
U?#
1@#
UA#
UB#
UC#
UD#
1E#
UF#
UG#
UH#
UI#
1J#
UK#
UL#
UM#
UN#
1O#
UP#
UQ#
UR#
US#
#5000000
b00001011 #
b11111101 $
1%
1&
1'
b00001011 1
b11111101 2
13
14
15
1<
b00000011 >
b00000000 @
b11111101 A
0C
0D
b00000011 H
b11111100 I
1J
b11111101 ""
b00000000 &"
1'"
0*"
0+"
b00000000 -"
1."
10"
01"
12"
14"
05"
16"
18"
09"
1:"
1<"
0="
1>"
1@"
0A"
1B"
1D"
0E"
1F"
1H"
0I"
1J"
1L"
0M"
1N"
b00001011 P"
1Q"
1R"
0V"
1W"
1Z"
1["
0\"
b0000101 ^"
1_"
1b"
0c"
b0000101 e"
1f"
1h"
1i"
0j"
1l"
0m"
1n"
1p"
1q"
0r"
1t"
0u"
1v"
1x"
0y"
1z"
1|"
0}"
1!#
1##
0$#
1%#
b00000000 '#
b11111101 (#
0*#
b000000000 +#
0-#
1.#
00#
02#
03#
04#
05#
07#
18#
09#
0:#
0<#
1=#
0>#
0?#
0A#
1B#
0C#
0D#
0F#
1G#
0H#
0I#
0K#
1L#
0M#
0N#
0P#
1Q#
0R#
0S#
#10000000
0%
0&
0'
0)
0+
03
04
05
07
09
0J
0'"
0("
0."
00"
04"
08"
0<"
0@"
0D"
0H"
0L"
0Q"
0S"
0Z"
0_"
0`"
b0001011 d"
0f"
0h"
1k"
0l"
0o"
0p"
1s"
0t"
0x"
0|"
0##
#15000000
b00010111 #
1%
1&
1'
b00010111 1
13
14
15
1J
1'"
1."
10"
14"
18"
1<"
1@"
1D"
1H"
1L"
b00010111 P"
1Q"
1Z"
b0001011 ^"
1_"
b0010111 d"
b0001011 e"
1f"
1h"
1l"
1m"
0n"
1o"
1p"
0q"
1r"
0s"
1t"
1u"
0v"
1w"
1x"
1|"
1##
#20000000
0%
0&
0'
03
04
05
0J
0'"
0."
00"
04"
08"
0<"
0@"
0D"
0H"
0L"
0Q"
0Z"
0_"
0f"
0h"
0l"
0p"
0t"
0x"
0|"
0##
#25000000
b00101111 #
1%
1&
1'
b00101111 1
13
14
15
1J
1'"
1."
10"
14"
18"
1<"
1@"
1D"
1H"
1L"
b00101111 P"
1Q"
1Z"
b0010111 ^"
1_"
b0101111 d"
b0010111 e"
1f"
1h"
1l"
1p"
1q"
0r"
1s"
1t"
0u"
1v"
0w"
1x"
1y"
0z"
1{"
1|"
1##
#30000000
0%
0&
0'
03
04
05
0J
0'"
0."
00"
04"
08"
0<"
0@"
0D"
0H"
0L"
0Q"
0Z"
0_"
0f"
0h"
0l"
0p"
0t"
0x"
0|"
0##
#35000000
b01011111 #
1%
1&
1'
b01011111 1
13
14
15
1J
1'"
1."
10"
14"
18"
1<"
1@"
1D"
1H"
1L"
b01011111 P"
1Q"
1Z"
b0101111 ^"
1_"
b1011111 d"
b0101111 e"
1f"
1h"
1l"
1p"
1t"
1u"
0v"
1w"
1x"
0y"
1z"
0{"
1|"
1}"
0!#
1"#
1##
#40000000
0%
0&
0'
03
04
05
0J
0'"
0."
00"
04"
08"
0<"
0@"
0D"
0H"
0L"
0Q"
0Z"
0_"
0f"
0h"
0l"
0p"
0t"
0x"
0|"
0##
#45000000
b10111111 #
1%
1&
1'
b10111111 1
13
14
15
1C
1J
1'"
1*"
b00000001 ,"
1."
1/"
10"
14"
18"
1<"
1@"
1D"
1H"
1L"
b10111111 P"
1Q"
1V"
1Z"
b1011111 ^"
1_"
1c"
b0111111 d"
b1011111 e"
1f"
1h"
1l"
1p"
1t"
1x"
1y"
0z"
1{"
1|"
0}"
1!#
0"#
1##
1$#
0%#
#50000000
0%
0&
0'
03
04
05
0J
0'"
0."
00"
04"
08"
0<"
0@"
0D"
0H"
0L"
0Q"
0Z"
0_"
0f"
0h"
0l"
0p"
0t"
0x"
0|"
0##
#55000000
b01111111 #
b11111110 $
1%
1&
1'
b01111111 1
b11111110 2
13
14
15
b00000001 @
b11111110 A
0C
1J
b11111110 ""
b00000001 &"
1'"
0*"
b00000010 ,"
b00000001 -"
1."
0/"
10"
11"
02"
13"
14"
18"
1<"
1@"
1D"
1H"
1L"
b01111111 P"
1Q"
0V"
1Z"
b0111111 ^"
1_"
0c"
b1111111 d"
b0111111 e"
1f"
1h"
1l"
1p"
1t"
1x"
1|"
1}"
0!#
1"#
1##
0$#
1%#
b00000001 '#
b11111110 (#
b000000010 +#
1-#
0.#
10#
13#
14#
#60000000
0%
0&
0'
03
04
05
0J
0'"
0."
00"
04"
08"
0<"
0@"
0D"
0H"
0L"
0Q"
0Z"
0_"
0f"
0h"
0l"
0p"
0t"
0x"
0|"
0##
#65000000
b11111111 #
b11111111 $
1%
1&
1'
b11111111 1
b11111111 2
13
14
15
1<
b00000010 @
b11111111 A
1C
0D
1J
b11111111 ""
b00000010 &"
1'"
1*"
b00000101 ,"
b00000010 -"
1."
1/"
10"
01"
12"
03"
14"
15"
06"
17"
18"
1<"
1@"
1D"
1H"
1L"
b11111111 P"
1Q"
1R"
1V"
1Z"
b1111111 ^"
1_"
1c"
b1111111 e"
1f"
1h"
1l"
1p"
1t"
1x"
1|"
1##
1$#
0%#
b00000010 '#
b11111111 (#
0*#
b000000000 +#
0-#
1.#
00#
12#
13#
04#
05#
18#
09#
0:#
1=#
0>#
0?#
1B#
0C#
0D#
1G#
0H#
0I#
1L#
0M#
0N#
1Q#
0R#
0S#
#70000000
0%
0&
0'
03
04
05
0J
0'"
0."
00"
04"
08"
0<"
0@"
0D"
0H"
0L"
0Q"
0Z"
0_"
0f"
0h"
0l"
0p"
0t"
0x"
0|"
0##
#75000000
b00000010 $
1%
1&
1'
b00000010 2
13
14
15
0<
b00000101 @
b00000010 A
1D
1J
b00000010 ""
b00000101 &"
1'"
b00001011 ,"
b00000101 -"
1."
10"
11"
02"
13"
14"
05"
16"
07"
18"
19"
0:"
1;"
1<"
1@"
1D"
1H"
1L"
1Q"
0R"
1Z"
1_"
1f"
1h"
1l"
1p"
1t"
1x"
1|"
1##
b00000101 '#
b00000010 (#
1*#
b111111010 +#
1-#
0.#
10#
02#
13#
14#
17#
08#
1:#
0=#
1>#
1?#
0B#
1C#
1D#
0G#
1H#
1I#
0L#
1M#
1N#
0Q#
1R#
1S#
#80000000
0%
0&
0'
03
04
05
0J
0'"
0."
00"
04"
08"
0<"
0@"
0D"
0H"
0L"
0Q"
0Z"
0_"
0f"
0h"
0l"
0p"
0t"
0x"
0|"
0##
